Metadata-Version: 1.1
Name: msworddictreplacer
Version: 0.0.1
Summary: python program to convert data dictionaries to replace fields in word document
Home-page: UNKNOWN
Author: Ashlin Darius Govindasamy
Author-email: adgrules@hotmail.com
License: MIT
Keywords: msword
Platform: UNKNOWN
Classifier: Development Status :: 5 - Production/Stable
Classifier: Intended Audience :: Education
Classifier: Operating System :: Microsoft :: Windows :: Windows 10
Classifier: License :: OSI Approved :: MIT License
Classifier: Programming Language :: Python :: 3
